<annotation>
	<folder>02_August_Gesa</folder>
	<filename>em_222.jpg</filename>
	<path>D:\ClarissaArbeit\EM\02_Exp\03_Methoden\02_Machine learningKavitha\03_ModifiedAnnotationsClarissa\02_August_Gesa\em_222.jpg</path>
	<source>
		<database>Unknown</database>
	</source>
	<size>
		<width>2048</width>
		<height>2048</height>
		<depth>1</depth>
	</size>
	<segmented>0</segmented>
	<object>
		<name>budding</name>
		<pose>Unspecified</pose>
		<truncated>0</truncated>
		<difficult>0</difficult>
		<bndbox>
			<xmin>1155</xmin>
			<ymin>526</ymin>
			<xmax>1225</xmax>
			<ymax>595</ymax>
		</bndbox>
	</object>
	<object>
		<name>budding</name>
		<pose>Unspecified</pose>
		<truncated>0</truncated>
		<difficult>0</difficult>
		<bndbox>
			<xmin>582</xmin>
			<ymin>1726</ymin>
			<xmax>647</xmax>
			<ymax>1795</ymax>
		</bndbox>
	</object>
	<object>
		<name>budding</name>
		<pose>Unspecified</pose>
		<truncated>0</truncated>
		<difficult>0</difficult>
		<bndbox>
			<xmin>840</xmin>
			<ymin>1771</ymin>
			<xmax>911</xmax>
			<ymax>1838</ymax>
		</bndbox>
	</object>
	<object>
		<name>budding</name>
		<pose>Unspecified</pose>
		<truncated>0</truncated>
		<difficult>0</difficult>
		<bndbox>
			<xmin>1609</xmin>
			<ymin>480</ymin>
			<xmax>1680</xmax>
			<ymax>545</ymax>
		</bndbox>
	</object>
</annotation>
